{"cameraMode":{"drawMode":0,"name":"Shaded","section":"Shading Mode"},"sceneLighting":true,"audioPlay":false,"sceneViewState":{"showFog":true,"showMaterialUpdate":false,"showSkybox":true,"showFlares":true,"showImageEffects":true,"showParticleSystems":true},"in2DMode":false,"pivot":{"x":-0.6778106093406677,"y":0.34266114234924319,"z":2.3825201988220217},"rotation":{"x":-0.1387520134449005,"y":0.8496608138084412,"z":-0.2757430374622345,"w":-0.4275434613227844},"size":2.0318520069122316,"orthographic":false}